staticwebsync/__init__.py
staticwebsync/sws.py
staticwebsync-1.1.1.dist-info/DESCRIPTION.rst
staticwebsync-1.1.1.dist-info/METADATA
staticwebsync-1.1.1.dist-info/RECORD
staticwebsync-1.1.1.dist-info/WHEEL
staticwebsync-1.1.1.dist-info/entry_points.txt
staticwebsync-1.1.1.dist-info/metadata.json
staticwebsync-1.1.1.dist-info/top_level.txt
