Metadata-Version: 2.0
Name: staticwebsync
Version: 1.1.1
Summary: Automates setting up S3/CloudFront for web site hosting
Home-page: http://staticwebsync.jjc1138.net/
Author: Jon Colverson
Author-email: staticwebsync@jjc1138.net
License: MIT
Keywords: S3 CloudFront AWS
Platform: UNKNOWN
Classifier: Development Status :: 5 - Production/Stable
Classifier: Environment :: Console
Classifier: Intended Audience :: Developers
Classifier: Intended Audience :: System Administrators
Classifier: License :: OSI Approved :: MIT License
Classifier: Natural Language :: English
Classifier: Programming Language :: Python :: 3 :: Only
Classifier: Topic :: Internet :: WWW/HTTP
Requires-Dist: boto3
Requires-Dist: colorama
Requires-Dist: termcolor
